rest_testing/__init__.py
rest_testing/api_test_case.py
rest_testing/api_view_test_scenario.py
django_rest_testing-0.1.0.dist-info/LICENSE
django_rest_testing-0.1.0.dist-info/METADATA
django_rest_testing-0.1.0.dist-info/WHEEL
django_rest_testing-0.1.0.dist-info/RECORD
