Metadata-Version: 2.1
Name: django-rest-testing
Version: 0.1.0
Summary: Declarative REST API Tests with Django.
Home-page: https://github.com/hbakri/django-rest-testing
License: MIT
Author: Hicham Bakri
Author-email: hicham.bakri76@gmail.com
Maintainer: Hicham Bakri
Maintainer-email: hicham.bakri76@gmail.com
Requires-Python: >=3.8,<4.0
Classifier: Development Status :: 4 - Beta
Classifier: Framework :: Django
Classifier: Framework :: Django :: 3.2
Classifier: Framework :: Django :: 4.1
Classifier: Framework :: Django :: 4.2
Classifier: Framework :: Django :: 5.0
Classifier: Intended Audience :: Developers
Classifier: License :: OSI Approved :: MIT License
Classifier: Programming Language :: Python
Classifier: Programming Language :: Python :: 3
Classifier: Programming Language :: Python :: 3.8
Classifier: Programming Language :: Python :: 3.9
Classifier: Programming Language :: Python :: 3.10
Classifier: Programming Language :: Python :: 3.11
Classifier: Programming Language :: Python :: 3.12
Classifier: Topic :: Software Development
Classifier: Topic :: Software Development :: Testing
Classifier: Typing :: Typed
Requires-Dist: django (>=3.2)
Requires-Dist: pydantic (>=2.0)
